Metadata-Version: 2.1
Name: pari-utils
Version: 0.0.0
Summary: utilities for PARI/GP
Home-page: https://gitlab.com/sagemath/pari-utils
Author: Vincent Delecroix
Author-email: vincent.delecroix@u-bordeaux.fr
License: GPL v3
Download-URL: https://pypi.org/project/pari-utils/#files
Keywords: PARI/GP
Platform: any
Classifier: License :: OSI Approved :: GNU General Public License v3 (GPLv3)
Classifier: Programming Language :: C++
Classifier: Programming Language :: Python
Classifier: Development Status :: 5 - Production/Stable
Classifier: Operating System :: Unix
Classifier: Intended Audience :: Science/Research
Classifier: Programming Language :: Python :: 3
Classifier: Programming Language :: Python :: 3.6
Classifier: Programming Language :: Python :: 3.7
